MANIFEST.in
README.md
setup.cfg
setup.py
py_yacc.egg-info/PKG-INFO
py_yacc.egg-info/SOURCES.txt
py_yacc.egg-info/dependency_links.txt
py_yacc.egg-info/entry_points.txt
py_yacc.egg-info/requires.txt
py_yacc.egg-info/top_level.txt
pyyacc/__init__.py
pyyacc/cfgparse.py
pyyacc/cstore.py
pyyacc/facades.py
pyyacc/parser.py
pyyacc/uritools.py
pyyacc/scripts/__init__.py
pyyacc/scripts/compile.py
pyyacc/yml/__init__.py
pyyacc/yml/extensions.py
pyyacc3/__init__.py
pyyacc3/cfgparse.py
pyyacc3/compile.py
pyyacc3/descriptor.py
pyyacc3/resolver.py
pyyacc3/yml/__init__.py
pyyacc3/yml/extensions.py