Metadata-Version: 2.1
Name: py-yacc
Version: 3.0.1
Summary: A YAML based configuration DSL and associated parser/validator.
Home-page: https://github.com/Livefyre/py-yacc
Author: Nino Walker
Author-email: nino.walker@gmail.com
License: BSD
Platform: UNKNOWN
Classifier: License :: OSI Approved :: BSD License
Provides-Extra: test
